build_kure
pyrel
