Metadata-Version: 2.1
Name: pyrel
Version: 0.2.0
Summary: An efficient python library for working with and manipulating binary relations.
Home-page: https://github.com/Peter-Roger/pyrel
Author: Peter Roger
License: GPLv3
Platform: darwin
Platform: linux
